sqlor/__init__.py
sqlor/aiomysqlor.py
sqlor/aiopostgresqlor.py
sqlor/aiosqliteor.py
sqlor/clickhouseor.py
sqlor/const.py
sqlor/crud.py
sqlor/dbloader.py
sqlor/dbpassword.py
sqlor/dbpools.old.py
sqlor/dbpools.py
sqlor/ddl_template_clickhouse.py
sqlor/ddl_template_duckdb.py
sqlor/ddl_template_mysql.py
sqlor/ddl_template_oracle.py
sqlor/ddl_template_postgresql.py
sqlor/ddl_template_sqlite3.py
sqlor/ddl_template_sqlserver.py
sqlor/duckdbor.py
sqlor/filter.py
sqlor/mssqlor.py
sqlor/mysqlor.py
sqlor/oracleor.py
sqlor/pgsqlor.py
sqlor/postgresqlor.py
sqlor/records.py
sqlor/runsql.py
sqlor/sor.py
sqlor/sqlite3or.py
sqlor/sqliteor.py
sqlor/tidbor.py
sqlor/version.py
sqlor-2.1.2.dist-info/METADATA
sqlor-2.1.2.dist-info/WHEEL
sqlor-2.1.2.dist-info/entry_points.txt
sqlor-2.1.2.dist-info/top_level.txt
sqlor-2.1.2.dist-info/RECORD
