Metadata-Version: 2.4
Name: sqlor
Version: 2.1.2
Summary: a new version of sqlor, each db's sor need to plugin to sqlor, and dbdriver now a isolated module
Author-email: yumoqing@gmail.com
License: {text = MIT}
Requires-Dist: aiomysql
Requires-Dist: aiopg
Requires-Dist: duckdb
Requires-Dist: clickhouse-driver
Requires-Dist: PyMySQL
Requires-Dist: aiosqlite
Requires-Dist: asyncio
Requires-Dist: jinja2
